MANIFEST.in
setup.py
requirements/run.txt
semi_ate_testers/LICENSE.txt
semi_ate_testers/README.md
semi_ate_testers/__init__.py
semi_ate_testers.egg-info/PKG-INFO
semi_ate_testers.egg-info/SOURCES.txt
semi_ate_testers.egg-info/dependency_links.txt
semi_ate_testers.egg-info/entry_points.txt
semi_ate_testers.egg-info/requires.txt
semi_ate_testers.egg-info/top_level.txt
semi_ate_testers/Flatcache/Flatcache.py
semi_ate_testers/Flatcache/__init__.py
semi_ate_testers/master_testers/__init__.py
semi_ate_testers/master_testers/dummy_master_parallel_tester.py
semi_ate_testers/master_testers/dummy_master_single_tester.py
semi_ate_testers/master_testers/tester_master_interface.py
semi_ate_testers/testers/__init__.py
semi_ate_testers/testers/dummy_minisct.py
semi_ate_testers/testers/dummy_parallel_tester.py
semi_ate_testers/testers/dummy_single_tester.py
semi_ate_testers/testers/file_configuration_tester.py
semi_ate_testers/testers/minisct.py
semi_ate_testers/testers/mqtt_minisct.py
semi_ate_testers/testers/tester_interface.py