Metadata-Version: 2.1
Name: semi-ate-testers
Version: 1.0.17
Summary: semi-ate-testers is an example implementation of a plugin that can be consumed by the semi-ate-spyder plugin and the master application.
Author: The Semi-ATE Project Contributors
Author-email: ate.organization@gmail.com
Requires-Dist: semi-ate-common
Requires-Dist: semi-ate-plugins
Requires-Dist: requests
Requires-Dist: pydantic
